mcp_cli/__init__.py
mcp_cli/cli.py
mcp_cli/config.py
mcp_cli/sse_client.py
mcp_cli/commands/ask.py
mcp_cli/commands/servers.py
mcp_hive_proxy-0.9.10.dist-info/METADATA
mcp_hive_proxy-0.9.10.dist-info/WHEEL
mcp_hive_proxy-0.9.10.dist-info/entry_points.txt
mcp_hive_proxy-0.9.10.dist-info/top_level.txt
mcp_hive_proxy-0.9.10.dist-info/RECORD
