Metadata-Version: 2.4
Name: mcp-hive-proxy
Version: 0.9.10
Summary: A powerful CLI for MCP servers with intelligent question matching, Windsurf integration, and comprehensive server management
Author-email: Trilogy Group <engineering@trilogy.com>
License: MIT
Project-URL: Homepage, https://github.com/trilogy-group/mcp-hive-proxy
Project-URL: Bug Tracker, https://github.com/trilogy-group/mcp-hive-proxy/issues
Classifier: Programming Language :: Python :: 3
Classifier: License :: OSI Approved :: MIT License
Classifier: Operating System :: OS Independent
Requires-Python: >=3.9
Requires-Dist: aiohttp>=3.8.0
Dynamic: requires-python
